subtidal/__init__.py
subtidal/cli.py
subtidal/download.py
subtidal-1.1.0.dist-info/LICENSE
subtidal-1.1.0.dist-info/METADATA
subtidal-1.1.0.dist-info/WHEEL
subtidal-1.1.0.dist-info/entry_points.txt
subtidal-1.1.0.dist-info/top_level.txt
subtidal-1.1.0.dist-info/RECORD
