Metadata-Version: 2.1
Name: subtidal
Version: 1.1.0
Summary: Subtidal, for batch downloading subtitles for all movies in a central media folder.
Home-page: https://github.com/athena15/subtidal
Author: Brenner Heintz
Author-email: brennerhdata@gmail.com
License: UNKNOWN
Platform: UNKNOWN
Classifier: Programming Language :: Python :: 3
Classifier: License :: OSI Approved :: MIT License
Classifier: Operating System :: OS Independent
Requires-Dist: Click (>=7.0)
Requires-Dist: pytest (>=4.4.1)
Requires-Dist: subliminal (>=2.0.5)
